MANIFEST.in
README.md
setup.py
simplegitweb/__init__.py
simplegitweb/__version__.py
simplegitweb/gitwebserver.py
simplegitweb.egg-info/PKG-INFO
simplegitweb.egg-info/SOURCES.txt
simplegitweb.egg-info/dependency_links.txt
simplegitweb.egg-info/not-zip-safe
simplegitweb.egg-info/requires.txt
simplegitweb.egg-info/top_level.txt
simplegitweb/systemd/gitwebserver.py
simplegitweb/systemd/install_service.sh
simplegitweb/systemd/simplegitweb.conf
simplegitweb/systemd/simplegitweb.service
simplegitweb/templates/add_new_repository.html
simplegitweb/templates/index_base.html