Metadata-Version: 2.1
Name: simplegitweb
Version: 0.1.6
Summary: A Python git web server that base on dulwich lib
Home-page: https://pypi.org/project/simplegitweb/
Author: dengyt
Author-email: dengyt@dengyt.net
License: Apache License, Version 2.0
Keywords: git gitserver gitweb version control
Platform: UNKNOWN
Classifier: Development Status :: 4 - Beta
Classifier: Programming Language :: Python :: 2.7
Classifier: Programming Language :: Python :: 3.3
Classifier: Programming Language :: Python :: 3.4
Classifier: Programming Language :: Python :: 3.5
Classifier: Programming Language :: Python :: 3.6
Classifier: Operating System :: POSIX
Classifier: Topic :: Software Development :: Version Control
